tsa_course/__init__.py
tsa_course/lecture1.py
tsa_course/lecture11.py
tsa_course/lecture2.py
tsa_course/lecture8.py
tsa_course-0.3.1.dist-info/licenses/LICENSE
tsa_course-0.3.1.dist-info/METADATA
tsa_course-0.3.1.dist-info/WHEEL
tsa_course-0.3.1.dist-info/top_level.txt
tsa_course-0.3.1.dist-info/RECORD
