Metadata-Version: 2.4
Name: tsa_course
Version: 0.3.1
Summary: A collection of scripts and functions used in the course 'Time Series Analysis with Python'
Author: Filippo Maria Bianchi
Author-email: filippombianchi@gmail.com
Project-URL: Documentation, https://filippomb.github.io/python-time-series-handbook
Project-URL: Source Code, https://github.com/FilippoMB/python-time-series-handbook
Classifier: Programming Language :: Python :: 3
Classifier: License :: OSI Approved :: MIT License
Classifier: Operating System :: OS Independent
Requires-Python: >=3.10
License-File: LICENSE
Requires-Dist: numpy>1.19.5
Requires-Dist: matplotlib
Requires-Dist: scipy
Requires-Dist: tqdm
Dynamic: author
Dynamic: author-email
Dynamic: classifier
Dynamic: description
Dynamic: description-content-type
Dynamic: license-file
Dynamic: project-url
Dynamic: requires-dist
Dynamic: requires-python
Dynamic: summary
